{"last_updated":"Sat Jan  3 05:12:31 UTC 2026","progs":[{"prog_name":"The Beauty of Japanese Swords: Famous Masterpieces","ep_name":"A Shogun's Treasure","expired_at":"2026-01-07T04:28:00Z","prog_url":"https://www3.nhk.or.jp/nhkworld/en/shows/beautyswords/","ep_url":"https://www3.nhk.or.jp/nhkworld/en/shows/6059008/"},{"prog_name":"The Beauty of Japanese Swords: Famous Masterpieces","ep_name":"Invocatory Carvings","expired_at":"2026-01-06T04:28:00Z","prog_url":"https://www3.nhk.or.jp/nhkworld/en/shows/beautyswords/","ep_url":"https://www3.nhk.or.jp/nhkworld/en/shows/6059007/"},{"prog_name":"The Beauty of Japanese Swords: Famous Masterpieces","ep_name":"The Power of a God","expired_at":"2026-01-05T04:28:00Z","prog_url":"https://www3.nhk.or.jp/nhkworld/en/shows/beautyswords/","ep_url":"https://www3.nhk.or.jp/nhkworld/en/shows/6059006/"},{"prog_name":"Science View","ep_name":"Special Episode: Laying the Groundwork for Wireless Power Transfer","expired_at":"2026-01-06T14:59:00Z","prog_url":"https://www3.nhk.or.jp/nhkworld/en/shows/scienceview/","ep_url":"https://www3.nhk.or.jp/nhkworld/en/shows/2015292/"},{"prog_name":"Japan's Top Inventions","ep_name":"Multihead Weighers / Aircraft Interior Products","expired_at":"2026-01-03T14:59:00Z","prog_url":"https://www3.nhk.or.jp/nhkworld/en/shows/topinventions/","ep_url":"https://www3.nhk.or.jp/nhkworld/en/shows/2091041/"},{"prog_name":"Japanology Plus","ep_name":"Uesugi Yozan: All for His People","expired_at":"2026-01-08T02:58:00Z","prog_url":"https://www3.nhk.or.jp/nhkworld/en/shows/japanologyplus/","ep_url":"https://www3.nhk.or.jp/nhkworld/en/shows/2032327/"},{"prog_name":"MATSURI: The Heartbeat of Japan","ep_name":"Hirosaki Neputa Matsuri: Hirosaki","expired_at":"2026-01-08T02:20:00Z","prog_url":"https://www3.nhk.or.jp/nhkworld/en/shows/matsuri_japan/","ep_url":"https://www3.nhk.or.jp/nhkworld/en/shows/6126019/"},{"prog_name":"Core Kyoto","ep_name":"Lake Biwa Canal: A Nearby Lake Boosts Life in the Ancient Capital","expired_at":"2026-01-08T00:58:00Z","prog_url":"https://www3.nhk.or.jp/nhkworld/en/shows/corekyoto/","ep_url":"https://www3.nhk.or.jp/nhkworld/en/shows/2029217/"},{"prog_name":"Hit the Road","ep_name":"Saitama","expired_at":"2026-01-07T15:30:00Z","prog_url":"https://www3.nhk.or.jp/nhkworld/en/shows/hit-road/","ep_url":"https://www3.nhk.or.jp/nhkworld/en/shows/6056004/"},{"prog_name":"On the Wings","ep_name":"Narita to Kumamoto Airport","expired_at":"2026-01-07T11:53:00Z","prog_url":"https://www3.nhk.or.jp/nhkworld/en/shows/wings/","ep_url":"https://www3.nhk.or.jp/nhkworld/en/shows/6054006/"},{"prog_name":"The World Heritage Sites in Japan","ep_name":"Forest Pilgrimages: Sacred Sites and Pilgrimage Routes in the Kii Mountain Range","expired_at":"2026-01-07T14:59:00Z","prog_url":"https://www3.nhk.or.jp/nhkworld/en/shows/japan_heritage/","ep_url":"https://www3.nhk.or.jp/nhkworld/en/shows/6214014/"},{"prog_name":"RAMEN JAPAN","ep_name":"Kumamoto","expired_at":"2026-01-07T05:30:00Z","prog_url":"https://www3.nhk.or.jp/nhkworld/en/shows/ramenjapan/","ep_url":"https://www3.nhk.or.jp/nhkworld/en/shows/6055015/"},{"prog_name":"MATSURI: The Heartbeat of Japan","ep_name":"Buzen Kagura Matsuri: Buzen","expired_at":"2026-01-07T02:20:00Z","prog_url":"https://www3.nhk.or.jp/nhkworld/en/shows/matsuri_japan/","ep_url":"https://www3.nhk.or.jp/nhkworld/en/shows/6126018/"},{"prog_name":"Hit the Road","ep_name":"Fukushima","expired_at":"2026-01-06T15:30:00Z","prog_url":"https://www3.nhk.or.jp/nhkworld/en/shows/hit-road/","ep_url":"https://www3.nhk.or.jp/nhkworld/en/shows/6056003/"},{"prog_name":"The World Heritage Sites in Japan","ep_name":"Intertwined Lives on Sea and Shore: Shiretoko, Hokkaido","expired_at":"2026-01-07T14:59:00Z","prog_url":"https://www3.nhk.or.jp/nhkworld/en/shows/japan_heritage/","ep_url":"https://www3.nhk.or.jp/nhkworld/en/shows/6214013/"},{"prog_name":"RAMEN JAPAN","ep_name":"Kagoshima","expired_at":"2026-01-06T05:30:00Z","prog_url":"https://www3.nhk.or.jp/nhkworld/en/shows/ramenjapan/","ep_url":"https://www3.nhk.or.jp/nhkworld/en/shows/6055014/"},{"prog_name":"Dig More Japan","ep_name":"Japanese Charms","expired_at":"2026-01-06T04:55:00Z","prog_url":"https://www3.nhk.or.jp/nhkworld/en/shows/digmorejapan/","ep_url":"https://www3.nhk.or.jp/nhkworld/en/shows/6122168/"},{"prog_name":"Hit the Road","ep_name":"Hiroshima","expired_at":"2026-01-05T15:30:00Z","prog_url":"https://www3.nhk.or.jp/nhkworld/en/shows/hit-road/","ep_url":"https://www3.nhk.or.jp/nhkworld/en/shows/6056001/"},{"prog_name":"On the Wings","ep_name":"Haneda to Fukuoka Airport","expired_at":"2026-01-05T11:53:00Z","prog_url":"https://www3.nhk.or.jp/nhkworld/en/shows/wings/","ep_url":"https://www3.nhk.or.jp/nhkworld/en/shows/6054003/"},{"prog_name":"The World Heritage Sites in Japan","ep_name":"Triangular Roofs Bring People Together: Historic Villages of Shirakawa-go and Gokayama","expired_at":"2026-01-07T14:59:00Z","prog_url":"https://www3.nhk.or.jp/nhkworld/en/shows/japan_heritage/","ep_url":"https://www3.nhk.or.jp/nhkworld/en/shows/6214012/"},{"prog_name":"CINEMATIC JOURNEY","ep_name":"Mt. Fuji Long Trail / OUTDOORS","expired_at":"2026-01-05T05:25:00Z","prog_url":"https://www3.nhk.or.jp/nhkworld/en/shows/cinematicjourney/","ep_url":"https://www3.nhk.or.jp/nhkworld/en/shows/6217004/"},{"prog_name":"Satoyama Kitchen Diary","ep_name":"Fancy and Flavorful Dried Persimmons","expired_at":"2026-01-05T05:00:00Z","prog_url":"https://www3.nhk.or.jp/nhkworld/en/shows/kitchendiary/","ep_url":"https://www3.nhk.or.jp/nhkworld/en/shows/6051009/"},{"prog_name":"Seasoning the Seasons","ep_name":"Sharing Happiness: Hot Pots in Japan","expired_at":"2026-01-05T02:58:00Z","prog_url":"https://www3.nhk.or.jp/nhkworld/en/shows/seasoning/","ep_url":"https://www3.nhk.or.jp/nhkworld/en/shows/2024133/"},{"prog_name":"MATSURI: The Heartbeat of Japan","ep_name":"Niihama Taiko Matsuri: Niihama","expired_at":"2026-01-05T02:20:00Z","prog_url":"https://www3.nhk.or.jp/nhkworld/en/shows/matsuri_japan/","ep_url":"https://www3.nhk.or.jp/nhkworld/en/shows/6126016/"},{"prog_name":"Time-lapse Japan","ep_name":"JOMON: The Sannai Maruyama Site","expired_at":"2026-01-05T01:15:00Z","prog_url":"https://www3.nhk.or.jp/nhkworld/en/shows/japantimelapse/","ep_url":"https://www3.nhk.or.jp/nhkworld/en/shows/6025025/"},{"prog_name":"Core Kyoto","ep_name":"Core Kyoto mini Maki-e: A Sumptuous World of Gold and Black","expired_at":"2026-01-04T05:30:00Z","prog_url":"https://www3.nhk.or.jp/nhkworld/en/shows/corekyoto/","ep_url":"https://www3.nhk.or.jp/nhkworld/en/shows/6024025/"},{"prog_name":"A Cat's-Eye View of Japan","ep_name":"Kagoshima: A Turtle, Tea Fields, and Cats","expired_at":"2026-01-04T03:00:00Z","prog_url":"https://www3.nhk.or.jp/nhkworld/en/shows/catseye/","ep_url":"https://www3.nhk.or.jp/nhkworld/en/shows/6045056/"},{"prog_name":"Japanology Plus mini","ep_name":"Kotatsu: Heated Tables","expired_at":"2026-01-04T02:55:00Z","prog_url":"https://www3.nhk.or.jp/nhkworld/en/shows/japanologymini/","ep_url":"https://www3.nhk.or.jp/nhkworld/en/shows/6032030/"},{"prog_name":"Time-lapse Journey","ep_name":"Kyoto","expired_at":"2026-01-03T14:38:00Z","prog_url":"https://www3.nhk.or.jp/nhkworld/en/shows/timelapsejourney/","ep_url":"https://www3.nhk.or.jp/nhkworld/en/shows/6048006/"},{"prog_name":"The World Heritage Sites in Japan","ep_name":"The Fabric of Life in a Forest: Shirakami-Sanchi","expired_at":"2026-01-07T14:59:00Z","prog_url":"https://www3.nhk.or.jp/nhkworld/en/shows/japan_heritage/","ep_url":"https://www3.nhk.or.jp/nhkworld/en/shows/6214011/"},{"prog_name":"Dive in Tokyo","ep_name":"Nihonbashi - The Mercantile Center of Old Tokyo","expired_at":"2026-01-07T14:59:00Z","prog_url":"https://www3.nhk.or.jp/nhkworld/en/shows/diveintokyo/","ep_url":"https://www3.nhk.or.jp/nhkworld/en/shows/2102042/"},{"prog_name":"Time-lapse Japan","ep_name":"YONEZAWA: \"Beni,\" Japanese Red","expired_at":"2026-01-05T14:59:00Z","prog_url":"https://www3.nhk.or.jp/nhkworld/en/shows/japantimelapse/","ep_url":"https://www3.nhk.or.jp/nhkworld/en/shows/6053013/"},{"prog_name":"Seasoning the Seasons","ep_name":"Sea of Okhotsk: Blessings of the Drift Ice","expired_at":"2026-01-05T14:59:00Z","prog_url":"https://www3.nhk.or.jp/nhkworld/en/shows/seasoning/","ep_url":"https://www3.nhk.or.jp/nhkworld/en/shows/2024159/"},{"prog_name":"HELLO! NHK WORLD-JAPAN","ep_name":"Special Series of Hokkaido in November","expired_at":"2026-01-05T14:59:00Z","prog_url":"https://www3.nhk.or.jp/nhkworld/en/shows/hello_nwj/","ep_url":"https://www3.nhk.or.jp/nhkworld/en/shows/2104043/"},{"prog_name":"Culture Crossroads","ep_name":"Helping Foreign Children to Integrate","expired_at":"2026-01-05T14:59:00Z","prog_url":"https://www3.nhk.or.jp/nhkworld/en/shows/culturecrossroads/","ep_url":"https://www3.nhk.or.jp/nhkworld/en/shows/2084064/"},{"prog_name":"FRONTRUNNERS","ep_name":"Wildlife Vet - Saito Keisuke","expired_at":"2026-01-07T14:59:00Z","prog_url":"https://www3.nhk.or.jp/nhkworld/en/shows/frontrunners/","ep_url":"https://www3.nhk.or.jp/nhkworld/en/shows/2103030/"},{"prog_name":"Document 72 Hours","ep_name":"Lives Inside a Huge \"Danchi\" Housing Complex","expired_at":"2026-01-06T14:59:00Z","prog_url":"https://www3.nhk.or.jp/nhkworld/en/shows/72hours/","ep_url":"https://www3.nhk.or.jp/nhkworld/en/shows/4026225/"},{"prog_name":"Documentary 360","ep_name":"The Sunflower Home: War Orphans of Nagasaki","expired_at":"2026-01-03T14:59:00Z","prog_url":"https://www3.nhk.or.jp/nhkworld/en/shows/sunflowerhome/","ep_url":"https://www3.nhk.or.jp/nhkworld/en/shows/5001339/"},{"prog_name":"Ukiyoe EDO-LIFE","ep_name":"Comfort Food on a Snowy Night","expired_at":"2026-01-07T12:00:00Z","prog_url":"https://www3.nhk.or.jp/nhkworld/en/shows/ukiyoeedolife/","ep_url":"https://www3.nhk.or.jp/nhkworld/en/shows/6030008/"},{"prog_name":"Ukiyoe EDO-LIFE","ep_name":"Two Faces of Mount Fuji","expired_at":"2026-01-06T12:00:00Z","prog_url":"https://www3.nhk.or.jp/nhkworld/en/shows/ukiyoeedolife/","ep_url":"https://www3.nhk.or.jp/nhkworld/en/shows/6030007/"},{"prog_name":"Ukiyoe EDO-LIFE","ep_name":"The Man with the Piercing Gaze","expired_at":"2026-01-05T12:00:00Z","prog_url":"https://www3.nhk.or.jp/nhkworld/en/shows/ukiyoeedolife/","ep_url":"https://www3.nhk.or.jp/nhkworld/en/shows/6030006/"},{"prog_name":"Trails to Oishii Tokyo","ep_name":"BEAN SPROUTS","expired_at":"2026-01-07T11:48:00Z","prog_url":"https://www3.nhk.or.jp/nhkworld/en/shows/oishii/","ep_url":"https://www3.nhk.or.jp/nhkworld/en/shows/6057006/"},{"prog_name":"Trails to Oishii Tokyo","ep_name":"KUZU","expired_at":"2026-01-06T11:48:00Z","prog_url":"https://www3.nhk.or.jp/nhkworld/en/shows/oishii/","ep_url":"https://www3.nhk.or.jp/nhkworld/en/shows/6057005/"},{"prog_name":"Dining with the Chef Mini","ep_name":"Cherry Blossom-shaped Crab Rice","expired_at":"2026-01-06T05:00:00Z","prog_url":"https://www3.nhk.or.jp/nhkworld/en/shows/dwcmini/","ep_url":"https://www3.nhk.or.jp/nhkworld/en/shows/6031023/"},{"prog_name":"Dining with the Chef","ep_name":"Master Chef's Class: Chef Hayashi's Japanese Traditional Appetizers","expired_at":"2026-01-06T01:58:00Z","prog_url":"https://www3.nhk.or.jp/nhkworld/en/shows/dwc/","ep_url":"https://www3.nhk.or.jp/nhkworld/en/shows/2019427/"},{"prog_name":"Trails to Oishii Tokyo","ep_name":"HORSEHAIR CRAB","expired_at":"2026-01-05T11:48:00Z","prog_url":"https://www3.nhk.or.jp/nhkworld/en/shows/oishii/","ep_url":"https://www3.nhk.or.jp/nhkworld/en/shows/6057004/"},{"prog_name":"EKIBEN JAPAN","ep_name":"Curry Framed by 400 Years of History","expired_at":"2026-01-07T14:59:00Z","prog_url":"https://www3.nhk.or.jp/nhkworld/en/shows/ekibenjapan/","ep_url":"https://www3.nhk.or.jp/nhkworld/en/shows/3025173/"},{"prog_name":"Dining with the Chef","ep_name":"Authentic Japanese Cooking: Yuan-yaki Salmon with Kinoko Miso","expired_at":"2026-01-06T14:59:00Z","prog_url":"https://www3.nhk.or.jp/nhkworld/en/shows/dwc/","ep_url":"https://www3.nhk.or.jp/nhkworld/en/shows/2019398/"},{"prog_name":"Little Charo","ep_name":"Season 2-17","expired_at":"2026-01-04T14:59:00Z","prog_url":"https://www3.nhk.or.jp/nhkworld/en/shows/littlecharo/","ep_url":"https://www3.nhk.or.jp/nhkworld/en/shows/6116040/"},{"prog_name":"Medical Frontiers","ep_name":"Nuclear Medicine to Treat Cancer","expired_at":"2026-01-05T14:59:00Z","prog_url":"https://www3.nhk.or.jp/nhkworld/en/shows/medicalfrontiers/","ep_url":"https://www3.nhk.or.jp/nhkworld/en/shows/2050167/"},{"prog_name":"Wild Hokkaido!","ep_name":"Canoeing Paradise - An Autumn Adventure on the Tokachi River","expired_at":"2026-01-04T14:59:00Z","prog_url":"https://www3.nhk.or.jp/nhkworld/en/shows/wildhokkaido/","ep_url":"https://www3.nhk.or.jp/nhkworld/en/shows/2069149/"},{"prog_name":"Journeys in Japan","ep_name":"Uchikawa: A retro river townscape","expired_at":"2026-01-06T00:58:00Z","prog_url":"https://www3.nhk.or.jp/nhkworld/en/shows/journeys/","ep_url":"https://www3.nhk.or.jp/nhkworld/en/shows/2007275/"}]}